[
    {
        "content": "<p>Alright, after some research, I've figured out how user defined data types, like structs or classes, are represented in memory.</p>\n<p>Now I have the issue of finding out how to use them with Cranelift.  Specifically, how do I use \"custom\" types as Values?  I know I can allocate them on the stack, but how can I return a custom data type, or use a custom data type as a function argument?  This would theoretically use registers, but how would I go about this in Cranelift?</p>",
        "id": 253853919,
        "sender_full_name": "Zack",
        "timestamp": 1631956611
    },
    {
        "content": "<p><span class=\"user-mention silent\" data-user-id=\"430718\">Zack</span> has marked this topic as resolved.</p>",
        "id": 253913020,
        "sender_full_name": "Notification Bot",
        "timestamp": 1632021793
    }
]