[
    {
        "content": "<p>How does one use <code>wasm-tools component semver-check</code>? For example, say I want to check that a  wasi-http change is sermver-compatible with the current interface. The CLI only seems to take one wit directory; is there a convenient way to copy the old world into the new wit directory? Or is there another way to do this?</p>",
        "id": 479738626,
        "sender_full_name": "Dan Gohman",
        "timestamp": 1730311770
    },
    {
        "content": "<p>the rough intention is that both the old and the new are in the same directory so you could do something like:</p>\n<div class=\"codehilite\" data-code-language=\"Rust\"><pre><span></span><code><span class=\"n\">wasm</span><span class=\"o\">-</span><span class=\"n\">tools</span><span class=\"w\"> </span><span class=\"n\">component</span><span class=\"w\"> </span><span class=\"n\">semver</span><span class=\"o\">-</span><span class=\"n\">check</span><span class=\"w\"> </span><span class=\"o\">--</span><span class=\"n\">prev</span><span class=\"w\"> </span><span class=\"n\">wasi</span><span class=\"p\">:</span><span class=\"nc\">http</span><span class=\"o\">/</span><span class=\"n\">proxy</span><span class=\"o\">@</span><span class=\"mf\">0.2.0</span><span class=\"w\"> </span><span class=\"o\">--</span><span class=\"n\">new</span><span class=\"w\"> </span><span class=\"n\">wasi</span><span class=\"p\">:</span><span class=\"nc\">http</span><span class=\"o\">/</span><span class=\"n\">proxy</span><span class=\"o\">@</span><span class=\"mf\">0.2.1</span><span class=\"w\"> </span><span class=\"p\">.</span><span class=\"o\">/</span><span class=\"n\">wit</span>\n</code></pre></div>\n<p>where you'd fill in <code>wit/deps/*</code> based on the various packages and dependencys (and probably a dummy <code>wit/root.wit</code> file for now)</p>",
        "id": 479739334,
        "sender_full_name": "Alex Crichton",
        "timestamp": 1730312045
    },
    {
        "content": "<p>How does one put two different versions of the same interfaces in wit/deps/* tree?</p>",
        "id": 479739615,
        "sender_full_name": "Dan Gohman",
        "timestamp": 1730312157
    },
    {
        "content": "<p>oh you can put them in separate folders, for example <code>wit/deps/http@0.2.0/*.wit</code> and <code>wit/deps/http@0.2.1/*.wit</code></p>",
        "id": 479740380,
        "sender_full_name": "Alex Crichton",
        "timestamp": 1730312453
    },
    {
        "content": "<p>the names of the directories don't actually matter, they're ignored during parsing -- only used for human-readable organization</p>",
        "id": 479740415,
        "sender_full_name": "Alex Crichton",
        "timestamp": 1730312468
    },
    {
        "content": "<div class=\"codehilite\" data-code-language=\"Rust\"><pre><span></span><code><span class=\"cp\">$</span><span class=\"w\"> </span><span class=\"n\">wasm</span><span class=\"o\">-</span><span class=\"n\">tools</span><span class=\"w\"> </span><span class=\"n\">component</span><span class=\"w\"> </span><span class=\"n\">semver</span><span class=\"o\">-</span><span class=\"n\">check</span><span class=\"w\"> </span><span class=\"o\">--</span><span class=\"n\">prev</span><span class=\"w\"> </span><span class=\"n\">wasi</span><span class=\"p\">:</span><span class=\"nc\">http</span><span class=\"o\">/</span><span class=\"n\">proxy</span><span class=\"o\">@</span><span class=\"mf\">0.2.2</span><span class=\"w\"> </span><span class=\"o\">--</span><span class=\"n\">new</span><span class=\"w\"> </span><span class=\"n\">wasi</span><span class=\"p\">:</span><span class=\"nc\">http</span><span class=\"o\">/</span><span class=\"n\">proxy</span><span class=\"o\">@</span><span class=\"mf\">0.2.3</span><span class=\"w\"> </span><span class=\"p\">.</span><span class=\"o\">/</span><span class=\"n\">wit</span>\n<span class=\"n\">error</span><span class=\"p\">:</span><span class=\"w\"> </span><span class=\"nc\">the</span><span class=\"w\"> </span><span class=\"n\">old</span><span class=\"w\"> </span><span class=\"n\">world</span><span class=\"w\"> </span><span class=\"n\">is</span><span class=\"w\"> </span><span class=\"k\">in</span><span class=\"w\"> </span><span class=\"n\">package</span><span class=\"w\"> </span><span class=\"n\">wasi</span><span class=\"p\">:</span><span class=\"nc\">http</span><span class=\"p\">,</span><span class=\"w\"> </span><span class=\"n\">which</span><span class=\"w\"> </span><span class=\"n\">is</span><span class=\"w\"> </span><span class=\"n\">not</span><span class=\"w\"> </span><span class=\"n\">the</span><span class=\"w\"> </span><span class=\"n\">same</span><span class=\"w\"> </span><span class=\"k\">as</span><span class=\"w\"> </span><span class=\"n\">the</span><span class=\"w\"> </span><span class=\"n\">new</span><span class=\"w\"> </span><span class=\"n\">world</span><span class=\"p\">,</span><span class=\"w\"> </span><span class=\"n\">which</span><span class=\"w\"> </span><span class=\"n\">is</span><span class=\"w\"> </span><span class=\"k\">in</span><span class=\"w\"> </span><span class=\"n\">package</span><span class=\"w\"> </span><span class=\"n\">wasi</span><span class=\"p\">:</span><span class=\"nc\">http</span>\n</code></pre></div>",
        "id": 479742387,
        "sender_full_name": "Dan Gohman",
        "timestamp": 1730313202
    },
    {
        "content": "<p>I think I got everything in versioned directories under wit/deps now, and am now getting this error.</p>",
        "id": 479743007,
        "sender_full_name": "Dan Gohman",
        "timestamp": 1730313435
    },
    {
        "content": "<p>One of them has <code>package wasi:http@0.2.2;</code> and the other has <code>package wasi:http@0.2.3;</code>.</p>",
        "id": 479743340,
        "sender_full_name": "Dan Gohman",
        "timestamp": 1730313561
    },
    {
        "content": "<p>This change seems to fix it for me. Does this look reasonable?</p>\n<div class=\"codehilite\" data-code-language=\"Diff\"><pre><span></span><code><span class=\"gh\">diff --git a/crates/wit-component/src/semver_check.rs b/crates/wit-component/src/semver_check.rs</span>\n<span class=\"gh\">index 1c4a9f4f..58d0aa74 100644</span>\n<span class=\"gd\">--- a/crates/wit-component/src/semver_check.rs</span>\n<span class=\"gi\">+++ b/crates/wit-component/src/semver_check.rs</span>\n<span class=\"gu\">@@ -55,7 +55,7 @@ pub fn semver_check(mut resolve: Resolve, prev: WorldId, new: WorldId) -&gt; Result</span>\n<span class=\"w\"> </span>        .package\n<span class=\"w\"> </span>        .context(\"new world not in named package\")?;\n<span class=\"w\"> </span>    let new_pkg_name = &amp;resolve.packages[new_pkg_id].name;\n<span class=\"gd\">-    if old_pkg_id != new_pkg_id {</span>\n<span class=\"gi\">+    if old_pkg_name != new_pkg_name {</span>\n<span class=\"w\"> </span>        bail!(\"the old world is in package {old_pkg_name}, which is not the same as the new world, which is in package {new_pkg_name}\", )\n<span class=\"w\"> </span>    }\n</code></pre></div>",
        "id": 479744945,
        "sender_full_name": "Dan Gohman",
        "timestamp": 1730314191
    },
    {
        "content": "<p>I've now added a test and posted this <a href=\"https://github.com/bytecodealliance/wasm-tools/pull/1886\">as a PR</a>.</p>\n<div class=\"message_embed\"><a class=\"message_embed_image\" href=\"https://github.com/bytecodealliance/wasm-tools/pull/1886\" style=\"background-image: url(&quot;https://uploads.zulipusercontent.net/c950ccafdbaaf67de105dc1b66bc038c9728d623/68747470733a2f2f6f70656e67726170682e6769746875626173736574732e636f6d2f653139646136323631323732643532383166613635646333306161333365353037393561313966646434363739333135313036636332616333373930383365372f62797465636f6465616c6c69616e63652f7761736d2d746f6f6c732f70756c6c2f31383836&quot;)\"></a><div class=\"data-container\"><div class=\"message_embed_title\"><a href=\"https://github.com/bytecodealliance/wasm-tools/pull/1886\" title=\"Relax semver-checks to compare worlds in packages with different versions by sunfishcode 路 Pull Request #1886 路 bytecodealliance/wasm-tools\">Relax semver-checks to compare worlds in packages with different versions by sunfishcode 路 Pull Request #1886 路 bytecodealliance/wasm-tools</a></div><div class=\"message_embed_description\">In wasm-tools component semver-checks, instead of requiring that the old and new world live in packages with the same id, just require that they have the same name. This allows checking for semver ...</div></div></div>",
        "id": 479748766,
        "sender_full_name": "Dan Gohman",
        "timestamp": 1730315696
    },
    {
        "content": "<p>oops yeah I think the check there is a bit overly cautious, thanks!</p>",
        "id": 479748808,
        "sender_full_name": "Alex Crichton",
        "timestamp": 1730315713
    }
]