[
    {
        "content": "<p>bjorn3 opened <a href=\"https://github.com/bytecodealliance/wasmtime/pull/7195\">PR #7195</a> from <code>bjorn3:backport_riscv_tls_fix</code> to <code>bytecodealliance:release-14.0.0</code>:</p>\n<blockquote>\n<p>Backport of <a href=\"https://github.com/bytecodealliance/wasmtime/pull/7177\">https://github.com/bytecodealliance/wasmtime/pull/7177</a></p>\n</blockquote>",
        "id": 395643209,
        "sender_full_name": "Wasmtime GitHub notifications bot",
        "timestamp": 1696839393
    },
    {
        "content": "<p><strong>bjorn3</strong> requested <a href=\"https://github.com/cfallin\">cfallin</a> for a review on <a href=\"https://github.com/bytecodealliance/wasmtime/pull/7195\">PR #7195</a>.</p>",
        "id": 395643213,
        "sender_full_name": "Wasmtime GitHub notifications bot",
        "timestamp": 1696839395
    },
    {
        "content": "<p><strong>bjorn3</strong> requested <a href=\"https://github.com/orgs/bytecodealliance/teams/wasmtime-compiler-reviewers\">wasmtime-compiler-reviewers</a> for a review on <a href=\"https://github.com/bytecodealliance/wasmtime/pull/7195\">PR #7195</a>.</p>",
        "id": 395643214,
        "sender_full_name": "Wasmtime GitHub notifications bot",
        "timestamp": 1696839395
    },
    {
        "content": "<p>alexcrichton submitted <a href=\"https://github.com/bytecodealliance/wasmtime/pull/7195#pullrequestreview-1664472022\">PR review</a>.</p>",
        "id": 395701201,
        "sender_full_name": "Wasmtime GitHub notifications bot",
        "timestamp": 1696858590
    },
    {
        "content": "<p>alexcrichton merged <a href=\"https://github.com/bytecodealliance/wasmtime/pull/7195\">PR #7195</a>.</p>",
        "id": 395701224,
        "sender_full_name": "Wasmtime GitHub notifications bot",
        "timestamp": 1696858596
    }
]