[
    {
        "content": "<p>afonso360 opened <a href=\"https://github.com/bytecodealliance/wasmtime/issues/5952\">issue #5952</a>:</p>\n<blockquote>\n<p><span aria-label=\"wave\" class=\"emoji emoji-1f44b\" role=\"img\" title=\"wave\">:wave:</span> Hey,</p>\n<p>I re-ran the fuzzer today with the issues that were fixed in the past weeks, and it reported some new cases.</p>\n<h3><code>.clif</code> Test Case</h3>\n<div class=\"codehilite\" data-code-language=\"Rust\"><pre><span></span><code><span class=\"n\">test</span><span class=\"w\"> </span><span class=\"n\">interpret</span>\n<span class=\"n\">test</span><span class=\"w\"> </span><span class=\"n\">run</span>\n<span class=\"n\">target</span><span class=\"w\"> </span><span class=\"n\">riscv64gc</span>\n\n<span class=\"n\">function</span><span class=\"w\"> </span><span class=\"o\">%</span><span class=\"n\">a</span><span class=\"p\">(</span><span class=\"kt\">i16</span><span class=\"w\"> </span><span class=\"n\">uext</span><span class=\"p\">)</span><span class=\"w\"> </span>-&gt; <span class=\"kt\">f32</span> <span class=\"p\">{</span>\n<span class=\"n\">block0</span><span class=\"p\">(</span><span class=\"n\">v0</span>: <span class=\"kt\">i16</span><span class=\"p\">)</span>:\n    <span class=\"nc\">v1</span><span class=\"w\"> </span><span class=\"o\">=</span><span class=\"w\"> </span><span class=\"n\">fcvt_from_sint</span><span class=\"p\">.</span><span class=\"kt\">f32</span><span class=\"w\"> </span><span class=\"n\">v0</span>\n<span class=\"w\">    </span><span class=\"k\">return</span><span class=\"w\"> </span><span class=\"n\">v1</span>\n<span class=\"p\">}</span>\n\n<span class=\"p\">;</span><span class=\"w\"> </span><span class=\"n\">run</span>: <span class=\"o\">%</span><span class=\"n\">a</span><span class=\"p\">(</span><span class=\"o\">-</span><span class=\"mi\">12800</span><span class=\"p\">)</span><span class=\"w\"> </span><span class=\"o\">==</span><span class=\"w\"> </span><span class=\"o\">-</span><span class=\"mh\">0x1</span><span class=\"p\">.</span><span class=\"mi\">900000</span><span class=\"n\">p13</span>\n</code></pre></div>\n<h3>Steps to Reproduce</h3>\n<ul>\n<li><code>clif-util test ./the-above.clif</code></li>\n</ul>\n<h3>Expected Results</h3>\n<p>The test to pass!</p>\n<h3>Actual Results</h3>\n<div class=\"codehilite\" data-code-language=\"Rust\"><pre><span></span><code><span class=\"w\"> </span><span class=\"n\">ERROR</span><span class=\"w\"> </span><span class=\"n\">cranelift_filetests</span>::<span class=\"n\">concurrent</span><span class=\"w\"> </span><span class=\"o\">&gt;</span><span class=\"w\"> </span><span class=\"n\">FAIL</span>: <span class=\"nc\">run</span>\n<span class=\"n\">FAIL</span><span class=\"w\"> </span><span class=\"p\">.</span><span class=\"o\">/</span><span class=\"n\">lmao</span><span class=\"p\">.</span><span class=\"n\">clif</span>: <span class=\"nc\">run</span>\n\n<span class=\"n\">Caused</span><span class=\"w\"> </span><span class=\"n\">by</span>:\n    <span class=\"nc\">Failed</span><span class=\"w\"> </span><span class=\"n\">test</span>: <span class=\"nc\">run</span>: <span class=\"o\">%</span><span class=\"n\">a</span><span class=\"p\">(</span><span class=\"o\">-</span><span class=\"mi\">12800</span><span class=\"p\">)</span><span class=\"w\"> </span><span class=\"o\">==</span><span class=\"w\"> </span><span class=\"o\">-</span><span class=\"mh\">0x1</span><span class=\"p\">.</span><span class=\"mi\">900000</span><span class=\"n\">p13</span><span class=\"p\">,</span><span class=\"w\"> </span><span class=\"n\">actual</span>: <span class=\"mh\">0x1</span><span class=\"p\">.</span><span class=\"mi\">9</span><span class=\"n\">c0000p15</span>\n<span class=\"mi\">1</span><span class=\"w\"> </span><span class=\"n\">tests</span>\n<span class=\"n\">Error</span>: <span class=\"mi\">1</span><span class=\"w\"> </span><span class=\"n\">failure</span>\n</code></pre></div>\n<h3>Versions and Environment</h3>\n<p>Cranelift version or commit: main</p>\n<p>Operating system: Linux</p>\n<p>Architecture: RISCV64GC</p>\n<h3>Extra Info</h3>\n<p>CC: @yuyang-ok <br>\n</p>\n</blockquote>",
        "id": 340155956,
        "sender_full_name": "Wasmtime GitHub notifications bot",
        "timestamp": 1678206834
    },
    {
        "content": "<p>afonso360 labeled <a href=\"https://github.com/bytecodealliance/wasmtime/issues/5952\">issue #5952</a>:</p>\n<blockquote>\n<p><span aria-label=\"wave\" class=\"emoji emoji-1f44b\" role=\"img\" title=\"wave\">:wave:</span> Hey,</p>\n<p>I re-ran the fuzzer today with the issues that were fixed in the past weeks, and it reported some new cases.</p>\n<h3><code>.clif</code> Test Case</h3>\n<div class=\"codehilite\" data-code-language=\"Rust\"><pre><span></span><code><span class=\"n\">test</span><span class=\"w\"> </span><span class=\"n\">interpret</span>\n<span class=\"n\">test</span><span class=\"w\"> </span><span class=\"n\">run</span>\n<span class=\"n\">target</span><span class=\"w\"> </span><span class=\"n\">riscv64gc</span>\n\n<span class=\"n\">function</span><span class=\"w\"> </span><span class=\"o\">%</span><span class=\"n\">a</span><span class=\"p\">(</span><span class=\"kt\">i16</span><span class=\"w\"> </span><span class=\"n\">uext</span><span class=\"p\">)</span><span class=\"w\"> </span>-&gt; <span class=\"kt\">f32</span> <span class=\"p\">{</span>\n<span class=\"n\">block0</span><span class=\"p\">(</span><span class=\"n\">v0</span>: <span class=\"kt\">i16</span><span class=\"p\">)</span>:\n    <span class=\"nc\">v1</span><span class=\"w\"> </span><span class=\"o\">=</span><span class=\"w\"> </span><span class=\"n\">fcvt_from_sint</span><span class=\"p\">.</span><span class=\"kt\">f32</span><span class=\"w\"> </span><span class=\"n\">v0</span>\n<span class=\"w\">    </span><span class=\"k\">return</span><span class=\"w\"> </span><span class=\"n\">v1</span>\n<span class=\"p\">}</span>\n\n<span class=\"p\">;</span><span class=\"w\"> </span><span class=\"n\">run</span>: <span class=\"o\">%</span><span class=\"n\">a</span><span class=\"p\">(</span><span class=\"o\">-</span><span class=\"mi\">12800</span><span class=\"p\">)</span><span class=\"w\"> </span><span class=\"o\">==</span><span class=\"w\"> </span><span class=\"o\">-</span><span class=\"mh\">0x1</span><span class=\"p\">.</span><span class=\"mi\">900000</span><span class=\"n\">p13</span>\n</code></pre></div>\n<h3>Steps to Reproduce</h3>\n<ul>\n<li><code>clif-util test ./the-above.clif</code></li>\n</ul>\n<h3>Expected Results</h3>\n<p>The test to pass!</p>\n<h3>Actual Results</h3>\n<div class=\"codehilite\" data-code-language=\"Rust\"><pre><span></span><code><span class=\"w\"> </span><span class=\"n\">ERROR</span><span class=\"w\"> </span><span class=\"n\">cranelift_filetests</span>::<span class=\"n\">concurrent</span><span class=\"w\"> </span><span class=\"o\">&gt;</span><span class=\"w\"> </span><span class=\"n\">FAIL</span>: <span class=\"nc\">run</span>\n<span class=\"n\">FAIL</span><span class=\"w\"> </span><span class=\"p\">.</span><span class=\"o\">/</span><span class=\"n\">lmao</span><span class=\"p\">.</span><span class=\"n\">clif</span>: <span class=\"nc\">run</span>\n\n<span class=\"n\">Caused</span><span class=\"w\"> </span><span class=\"n\">by</span>:\n    <span class=\"nc\">Failed</span><span class=\"w\"> </span><span class=\"n\">test</span>: <span class=\"nc\">run</span>: <span class=\"o\">%</span><span class=\"n\">a</span><span class=\"p\">(</span><span class=\"o\">-</span><span class=\"mi\">12800</span><span class=\"p\">)</span><span class=\"w\"> </span><span class=\"o\">==</span><span class=\"w\"> </span><span class=\"o\">-</span><span class=\"mh\">0x1</span><span class=\"p\">.</span><span class=\"mi\">900000</span><span class=\"n\">p13</span><span class=\"p\">,</span><span class=\"w\"> </span><span class=\"n\">actual</span>: <span class=\"mh\">0x1</span><span class=\"p\">.</span><span class=\"mi\">9</span><span class=\"n\">c0000p15</span>\n<span class=\"mi\">1</span><span class=\"w\"> </span><span class=\"n\">tests</span>\n<span class=\"n\">Error</span>: <span class=\"mi\">1</span><span class=\"w\"> </span><span class=\"n\">failure</span>\n</code></pre></div>\n<h3>Versions and Environment</h3>\n<p>Cranelift version or commit: main</p>\n<p>Operating system: Linux</p>\n<p>Architecture: RISCV64GC</p>\n<h3>Extra Info</h3>\n<p>CC: @yuyang-ok <br>\n</p>\n</blockquote>",
        "id": 340155957,
        "sender_full_name": "Wasmtime GitHub notifications bot",
        "timestamp": 1678206834
    },
    {
        "content": "<p>afonso360 labeled <a href=\"https://github.com/bytecodealliance/wasmtime/issues/5952\">issue #5952</a>:</p>\n<blockquote>\n<p><span aria-label=\"wave\" class=\"emoji emoji-1f44b\" role=\"img\" title=\"wave\">:wave:</span> Hey,</p>\n<p>I re-ran the fuzzer today with the issues that were fixed in the past weeks, and it reported some new cases.</p>\n<h3><code>.clif</code> Test Case</h3>\n<div class=\"codehilite\" data-code-language=\"Rust\"><pre><span></span><code><span class=\"n\">test</span><span class=\"w\"> </span><span class=\"n\">interpret</span>\n<span class=\"n\">test</span><span class=\"w\"> </span><span class=\"n\">run</span>\n<span class=\"n\">target</span><span class=\"w\"> </span><span class=\"n\">riscv64gc</span>\n\n<span class=\"n\">function</span><span class=\"w\"> </span><span class=\"o\">%</span><span class=\"n\">a</span><span class=\"p\">(</span><span class=\"kt\">i16</span><span class=\"w\"> </span><span class=\"n\">uext</span><span class=\"p\">)</span><span class=\"w\"> </span>-&gt; <span class=\"kt\">f32</span> <span class=\"p\">{</span>\n<span class=\"n\">block0</span><span class=\"p\">(</span><span class=\"n\">v0</span>: <span class=\"kt\">i16</span><span class=\"p\">)</span>:\n    <span class=\"nc\">v1</span><span class=\"w\"> </span><span class=\"o\">=</span><span class=\"w\"> </span><span class=\"n\">fcvt_from_sint</span><span class=\"p\">.</span><span class=\"kt\">f32</span><span class=\"w\"> </span><span class=\"n\">v0</span>\n<span class=\"w\">    </span><span class=\"k\">return</span><span class=\"w\"> </span><span class=\"n\">v1</span>\n<span class=\"p\">}</span>\n\n<span class=\"p\">;</span><span class=\"w\"> </span><span class=\"n\">run</span>: <span class=\"o\">%</span><span class=\"n\">a</span><span class=\"p\">(</span><span class=\"o\">-</span><span class=\"mi\">12800</span><span class=\"p\">)</span><span class=\"w\"> </span><span class=\"o\">==</span><span class=\"w\"> </span><span class=\"o\">-</span><span class=\"mh\">0x1</span><span class=\"p\">.</span><span class=\"mi\">900000</span><span class=\"n\">p13</span>\n</code></pre></div>\n<h3>Steps to Reproduce</h3>\n<ul>\n<li><code>clif-util test ./the-above.clif</code></li>\n</ul>\n<h3>Expected Results</h3>\n<p>The test to pass!</p>\n<h3>Actual Results</h3>\n<div class=\"codehilite\" data-code-language=\"Rust\"><pre><span></span><code><span class=\"w\"> </span><span class=\"n\">ERROR</span><span class=\"w\"> </span><span class=\"n\">cranelift_filetests</span>::<span class=\"n\">concurrent</span><span class=\"w\"> </span><span class=\"o\">&gt;</span><span class=\"w\"> </span><span class=\"n\">FAIL</span>: <span class=\"nc\">run</span>\n<span class=\"n\">FAIL</span><span class=\"w\"> </span><span class=\"p\">.</span><span class=\"o\">/</span><span class=\"n\">lmao</span><span class=\"p\">.</span><span class=\"n\">clif</span>: <span class=\"nc\">run</span>\n\n<span class=\"n\">Caused</span><span class=\"w\"> </span><span class=\"n\">by</span>:\n    <span class=\"nc\">Failed</span><span class=\"w\"> </span><span class=\"n\">test</span>: <span class=\"nc\">run</span>: <span class=\"o\">%</span><span class=\"n\">a</span><span class=\"p\">(</span><span class=\"o\">-</span><span class=\"mi\">12800</span><span class=\"p\">)</span><span class=\"w\"> </span><span class=\"o\">==</span><span class=\"w\"> </span><span class=\"o\">-</span><span class=\"mh\">0x1</span><span class=\"p\">.</span><span class=\"mi\">900000</span><span class=\"n\">p13</span><span class=\"p\">,</span><span class=\"w\"> </span><span class=\"n\">actual</span>: <span class=\"mh\">0x1</span><span class=\"p\">.</span><span class=\"mi\">9</span><span class=\"n\">c0000p15</span>\n<span class=\"mi\">1</span><span class=\"w\"> </span><span class=\"n\">tests</span>\n<span class=\"n\">Error</span>: <span class=\"mi\">1</span><span class=\"w\"> </span><span class=\"n\">failure</span>\n</code></pre></div>\n<h3>Versions and Environment</h3>\n<p>Cranelift version or commit: main</p>\n<p>Operating system: Linux</p>\n<p>Architecture: RISCV64GC</p>\n<h3>Extra Info</h3>\n<p>CC: @yuyang-ok <br>\n</p>\n</blockquote>",
        "id": 340155958,
        "sender_full_name": "Wasmtime GitHub notifications bot",
        "timestamp": 1678206834
    },
    {
        "content": "<p>afonso360 labeled <a href=\"https://github.com/bytecodealliance/wasmtime/issues/5952\">issue #5952</a>:</p>\n<blockquote>\n<p><span aria-label=\"wave\" class=\"emoji emoji-1f44b\" role=\"img\" title=\"wave\">:wave:</span> Hey,</p>\n<p>I re-ran the fuzzer today with the issues that were fixed in the past weeks, and it reported some new cases.</p>\n<h3><code>.clif</code> Test Case</h3>\n<div class=\"codehilite\" data-code-language=\"Rust\"><pre><span></span><code><span class=\"n\">test</span><span class=\"w\"> </span><span class=\"n\">interpret</span>\n<span class=\"n\">test</span><span class=\"w\"> </span><span class=\"n\">run</span>\n<span class=\"n\">target</span><span class=\"w\"> </span><span class=\"n\">riscv64gc</span>\n\n<span class=\"n\">function</span><span class=\"w\"> </span><span class=\"o\">%</span><span class=\"n\">a</span><span class=\"p\">(</span><span class=\"kt\">i16</span><span class=\"w\"> </span><span class=\"n\">uext</span><span class=\"p\">)</span><span class=\"w\"> </span>-&gt; <span class=\"kt\">f32</span> <span class=\"p\">{</span>\n<span class=\"n\">block0</span><span class=\"p\">(</span><span class=\"n\">v0</span>: <span class=\"kt\">i16</span><span class=\"p\">)</span>:\n    <span class=\"nc\">v1</span><span class=\"w\"> </span><span class=\"o\">=</span><span class=\"w\"> </span><span class=\"n\">fcvt_from_sint</span><span class=\"p\">.</span><span class=\"kt\">f32</span><span class=\"w\"> </span><span class=\"n\">v0</span>\n<span class=\"w\">    </span><span class=\"k\">return</span><span class=\"w\"> </span><span class=\"n\">v1</span>\n<span class=\"p\">}</span>\n\n<span class=\"p\">;</span><span class=\"w\"> </span><span class=\"n\">run</span>: <span class=\"o\">%</span><span class=\"n\">a</span><span class=\"p\">(</span><span class=\"o\">-</span><span class=\"mi\">12800</span><span class=\"p\">)</span><span class=\"w\"> </span><span class=\"o\">==</span><span class=\"w\"> </span><span class=\"o\">-</span><span class=\"mh\">0x1</span><span class=\"p\">.</span><span class=\"mi\">900000</span><span class=\"n\">p13</span>\n</code></pre></div>\n<h3>Steps to Reproduce</h3>\n<ul>\n<li><code>clif-util test ./the-above.clif</code></li>\n</ul>\n<h3>Expected Results</h3>\n<p>The test to pass!</p>\n<h3>Actual Results</h3>\n<div class=\"codehilite\" data-code-language=\"Rust\"><pre><span></span><code><span class=\"w\"> </span><span class=\"n\">ERROR</span><span class=\"w\"> </span><span class=\"n\">cranelift_filetests</span>::<span class=\"n\">concurrent</span><span class=\"w\"> </span><span class=\"o\">&gt;</span><span class=\"w\"> </span><span class=\"n\">FAIL</span>: <span class=\"nc\">run</span>\n<span class=\"n\">FAIL</span><span class=\"w\"> </span><span class=\"p\">.</span><span class=\"o\">/</span><span class=\"n\">lmao</span><span class=\"p\">.</span><span class=\"n\">clif</span>: <span class=\"nc\">run</span>\n\n<span class=\"n\">Caused</span><span class=\"w\"> </span><span class=\"n\">by</span>:\n    <span class=\"nc\">Failed</span><span class=\"w\"> </span><span class=\"n\">test</span>: <span class=\"nc\">run</span>: <span class=\"o\">%</span><span class=\"n\">a</span><span class=\"p\">(</span><span class=\"o\">-</span><span class=\"mi\">12800</span><span class=\"p\">)</span><span class=\"w\"> </span><span class=\"o\">==</span><span class=\"w\"> </span><span class=\"o\">-</span><span class=\"mh\">0x1</span><span class=\"p\">.</span><span class=\"mi\">900000</span><span class=\"n\">p13</span><span class=\"p\">,</span><span class=\"w\"> </span><span class=\"n\">actual</span>: <span class=\"mh\">0x1</span><span class=\"p\">.</span><span class=\"mi\">9</span><span class=\"n\">c0000p15</span>\n<span class=\"mi\">1</span><span class=\"w\"> </span><span class=\"n\">tests</span>\n<span class=\"n\">Error</span>: <span class=\"mi\">1</span><span class=\"w\"> </span><span class=\"n\">failure</span>\n</code></pre></div>\n<h3>Versions and Environment</h3>\n<p>Cranelift version or commit: main</p>\n<p>Operating system: Linux</p>\n<p>Architecture: RISCV64GC</p>\n<h3>Extra Info</h3>\n<p>CC: @yuyang-ok <br>\n</p>\n</blockquote>",
        "id": 340155959,
        "sender_full_name": "Wasmtime GitHub notifications bot",
        "timestamp": 1678206834
    },
    {
        "content": "<p>afonso360 edited <a href=\"https://github.com/bytecodealliance/wasmtime/issues/5952\">issue #5952</a>:</p>\n<blockquote>\n<p><span aria-label=\"wave\" class=\"emoji emoji-1f44b\" role=\"img\" title=\"wave\">:wave:</span> Hey,</p>\n<p>I re-ran the fuzzer today with the issues that were fixed in the past weeks, and it reported some new cases.</p>\n<h3><code>.clif</code> Test Case</h3>\n<div class=\"codehilite\" data-code-language=\"Rust\"><pre><span></span><code><span class=\"n\">test</span><span class=\"w\"> </span><span class=\"n\">interpret</span>\n<span class=\"n\">test</span><span class=\"w\"> </span><span class=\"n\">run</span>\n<span class=\"n\">target</span><span class=\"w\"> </span><span class=\"n\">riscv64gc</span>\n\n<span class=\"n\">function</span><span class=\"w\"> </span><span class=\"o\">%</span><span class=\"n\">a</span><span class=\"p\">(</span><span class=\"kt\">i16</span><span class=\"w\"> </span><span class=\"n\">uext</span><span class=\"p\">)</span><span class=\"w\"> </span>-&gt; <span class=\"kt\">f32</span> <span class=\"p\">{</span>\n<span class=\"n\">block0</span><span class=\"p\">(</span><span class=\"n\">v0</span>: <span class=\"kt\">i16</span><span class=\"p\">)</span>:\n    <span class=\"nc\">v1</span><span class=\"w\"> </span><span class=\"o\">=</span><span class=\"w\"> </span><span class=\"n\">fcvt_from_sint</span><span class=\"p\">.</span><span class=\"kt\">f32</span><span class=\"w\"> </span><span class=\"n\">v0</span>\n<span class=\"w\">    </span><span class=\"k\">return</span><span class=\"w\"> </span><span class=\"n\">v1</span>\n<span class=\"p\">}</span>\n\n<span class=\"p\">;</span><span class=\"w\"> </span><span class=\"n\">run</span>: <span class=\"o\">%</span><span class=\"n\">a</span><span class=\"p\">(</span><span class=\"o\">-</span><span class=\"mi\">12800</span><span class=\"p\">)</span><span class=\"w\"> </span><span class=\"o\">==</span><span class=\"w\"> </span><span class=\"o\">-</span><span class=\"mh\">0x1</span><span class=\"p\">.</span><span class=\"mi\">900000</span><span class=\"n\">p13</span>\n</code></pre></div>\n<h3>Steps to Reproduce</h3>\n<ul>\n<li><code>clif-util test ./the-above.clif</code></li>\n</ul>\n<h3>Expected Results</h3>\n<p>The test to pass!</p>\n<h3>Actual Results</h3>\n<div class=\"codehilite\" data-code-language=\"Rust\"><pre><span></span><code><span class=\"w\"> </span><span class=\"n\">ERROR</span><span class=\"w\"> </span><span class=\"n\">cranelift_filetests</span>::<span class=\"n\">concurrent</span><span class=\"w\"> </span><span class=\"o\">&gt;</span><span class=\"w\"> </span><span class=\"n\">FAIL</span>: <span class=\"nc\">run</span>\n<span class=\"n\">FAIL</span><span class=\"w\"> </span><span class=\"p\">.</span><span class=\"o\">/</span><span class=\"n\">lmao</span><span class=\"p\">.</span><span class=\"n\">clif</span>: <span class=\"nc\">run</span>\n\n<span class=\"n\">Caused</span><span class=\"w\"> </span><span class=\"n\">by</span>:\n    <span class=\"nc\">Failed</span><span class=\"w\"> </span><span class=\"n\">test</span>: <span class=\"nc\">run</span>: <span class=\"o\">%</span><span class=\"n\">a</span><span class=\"p\">(</span><span class=\"o\">-</span><span class=\"mi\">12800</span><span class=\"p\">)</span><span class=\"w\"> </span><span class=\"o\">==</span><span class=\"w\"> </span><span class=\"o\">-</span><span class=\"mh\">0x1</span><span class=\"p\">.</span><span class=\"mi\">900000</span><span class=\"n\">p13</span><span class=\"p\">,</span><span class=\"w\"> </span><span class=\"n\">actual</span>: <span class=\"mh\">0x1</span><span class=\"p\">.</span><span class=\"mi\">9</span><span class=\"n\">c0000p15</span>\n<span class=\"mi\">1</span><span class=\"w\"> </span><span class=\"n\">tests</span>\n<span class=\"n\">Error</span>: <span class=\"mi\">1</span><span class=\"w\"> </span><span class=\"n\">failure</span>\n</code></pre></div>\n<h3>Versions and Environment</h3>\n<p>Cranelift version or commit: main (e2dcb19099606f161c6d6145ba71130579b452e2)</p>\n<p>Operating system: Linux</p>\n<p>Architecture: RISCV64GC</p>\n<h3>Extra Info</h3>\n<p>CC: @yuyang-ok <br>\n</p>\n</blockquote>",
        "id": 340156174,
        "sender_full_name": "Wasmtime GitHub notifications bot",
        "timestamp": 1678206883
    },
    {
        "content": "<p>yuyang-ok <a href=\"https://github.com/bytecodealliance/wasmtime/issues/5952#issuecomment-1459592824\">commented</a> on <a href=\"https://github.com/bytecodealliance/wasmtime/issues/5952\">issue #5952</a>:</p>\n<blockquote>\n<p>@afonso360 <span aria-label=\"+1\" class=\"emoji emoji-1f44d\" role=\"img\" title=\"+1\">:+1:</span></p>\n</blockquote>",
        "id": 340273908,
        "sender_full_name": "Wasmtime GitHub notifications bot",
        "timestamp": 1678255372
    },
    {
        "content": "<p>yuyang-ok <a href=\"https://github.com/bytecodealliance/wasmtime/issues/5952#issuecomment-1459598004\">commented</a> on <a href=\"https://github.com/bytecodealliance/wasmtime/issues/5952\">issue #5952</a>:</p>\n<blockquote>\n<p>@afonso360   Looking at the <code>ISLE</code> lowering rules.I think we should extend value first.</p>\n</blockquote>",
        "id": 340274632,
        "sender_full_name": "Wasmtime GitHub notifications bot",
        "timestamp": 1678255781
    },
    {
        "content": "<p>yuyang-ok edited a <a href=\"https://github.com/bytecodealliance/wasmtime/issues/5952#issuecomment-1459598004\">comment</a> on <a href=\"https://github.com/bytecodealliance/wasmtime/issues/5952\">issue #5952</a>:</p>\n<blockquote>\n<p>@afonso360   Looking at the <code>ISLE</code> lowering rules.I think we should extend <code>from</code> value first.</p>\n</blockquote>",
        "id": 340275379,
        "sender_full_name": "Wasmtime GitHub notifications bot",
        "timestamp": 1678256240
    },
    {
        "content": "<p>yuyang-ok deleted a <a href=\"https://github.com/bytecodealliance/wasmtime/issues/5952#issuecomment-1459592824\">comment</a> on <a href=\"https://github.com/bytecodealliance/wasmtime/issues/5952\">issue #5952</a>:</p>\n<blockquote>\n<p>@afonso360 <span aria-label=\"+1\" class=\"emoji emoji-1f44d\" role=\"img\" title=\"+1\">:+1:</span></p>\n</blockquote>",
        "id": 340301082,
        "sender_full_name": "Wasmtime GitHub notifications bot",
        "timestamp": 1678266054
    },
    {
        "content": "<p>yuyang-ok <a href=\"https://github.com/bytecodealliance/wasmtime/issues/5952#issuecomment-1461340757\">commented</a> on <a href=\"https://github.com/bytecodealliance/wasmtime/issues/5952\">issue #5952</a>:</p>\n<blockquote>\n<p>@afonso360 Maybe a review. <a href=\"https://github.com/bytecodealliance/wasmtime/pull/5964\">#5964 </a></p>\n</blockquote>",
        "id": 340519848,
        "sender_full_name": "Wasmtime GitHub notifications bot",
        "timestamp": 1678342050
    },
    {
        "content": "<p>afonso360 closed <a href=\"https://github.com/bytecodealliance/wasmtime/issues/5952\">issue #5952</a>:</p>\n<blockquote>\n<p><span aria-label=\"wave\" class=\"emoji emoji-1f44b\" role=\"img\" title=\"wave\">:wave:</span> Hey,</p>\n<p>I re-ran the fuzzer today with the issues that were fixed in the past weeks, and it reported some new cases.</p>\n<h3><code>.clif</code> Test Case</h3>\n<div class=\"codehilite\" data-code-language=\"Rust\"><pre><span></span><code><span class=\"n\">test</span><span class=\"w\"> </span><span class=\"n\">interpret</span>\n<span class=\"n\">test</span><span class=\"w\"> </span><span class=\"n\">run</span>\n<span class=\"n\">target</span><span class=\"w\"> </span><span class=\"n\">riscv64gc</span>\n\n<span class=\"n\">function</span><span class=\"w\"> </span><span class=\"o\">%</span><span class=\"n\">a</span><span class=\"p\">(</span><span class=\"kt\">i16</span><span class=\"w\"> </span><span class=\"n\">uext</span><span class=\"p\">)</span><span class=\"w\"> </span>-&gt; <span class=\"kt\">f32</span> <span class=\"p\">{</span>\n<span class=\"n\">block0</span><span class=\"p\">(</span><span class=\"n\">v0</span>: <span class=\"kt\">i16</span><span class=\"p\">)</span>:\n    <span class=\"nc\">v1</span><span class=\"w\"> </span><span class=\"o\">=</span><span class=\"w\"> </span><span class=\"n\">fcvt_from_sint</span><span class=\"p\">.</span><span class=\"kt\">f32</span><span class=\"w\"> </span><span class=\"n\">v0</span>\n<span class=\"w\">    </span><span class=\"k\">return</span><span class=\"w\"> </span><span class=\"n\">v1</span>\n<span class=\"p\">}</span>\n\n<span class=\"p\">;</span><span class=\"w\"> </span><span class=\"n\">run</span>: <span class=\"o\">%</span><span class=\"n\">a</span><span class=\"p\">(</span><span class=\"o\">-</span><span class=\"mi\">12800</span><span class=\"p\">)</span><span class=\"w\"> </span><span class=\"o\">==</span><span class=\"w\"> </span><span class=\"o\">-</span><span class=\"mh\">0x1</span><span class=\"p\">.</span><span class=\"mi\">900000</span><span class=\"n\">p13</span>\n</code></pre></div>\n<h3>Steps to Reproduce</h3>\n<ul>\n<li><code>clif-util test ./the-above.clif</code></li>\n</ul>\n<h3>Expected Results</h3>\n<p>The test to pass!</p>\n<h3>Actual Results</h3>\n<div class=\"codehilite\" data-code-language=\"Rust\"><pre><span></span><code><span class=\"w\"> </span><span class=\"n\">ERROR</span><span class=\"w\"> </span><span class=\"n\">cranelift_filetests</span>::<span class=\"n\">concurrent</span><span class=\"w\"> </span><span class=\"o\">&gt;</span><span class=\"w\"> </span><span class=\"n\">FAIL</span>: <span class=\"nc\">run</span>\n<span class=\"n\">FAIL</span><span class=\"w\"> </span><span class=\"p\">.</span><span class=\"o\">/</span><span class=\"n\">lmao</span><span class=\"p\">.</span><span class=\"n\">clif</span>: <span class=\"nc\">run</span>\n\n<span class=\"n\">Caused</span><span class=\"w\"> </span><span class=\"n\">by</span>:\n    <span class=\"nc\">Failed</span><span class=\"w\"> </span><span class=\"n\">test</span>: <span class=\"nc\">run</span>: <span class=\"o\">%</span><span class=\"n\">a</span><span class=\"p\">(</span><span class=\"o\">-</span><span class=\"mi\">12800</span><span class=\"p\">)</span><span class=\"w\"> </span><span class=\"o\">==</span><span class=\"w\"> </span><span class=\"o\">-</span><span class=\"mh\">0x1</span><span class=\"p\">.</span><span class=\"mi\">900000</span><span class=\"n\">p13</span><span class=\"p\">,</span><span class=\"w\"> </span><span class=\"n\">actual</span>: <span class=\"mh\">0x1</span><span class=\"p\">.</span><span class=\"mi\">9</span><span class=\"n\">c0000p15</span>\n<span class=\"mi\">1</span><span class=\"w\"> </span><span class=\"n\">tests</span>\n<span class=\"n\">Error</span>: <span class=\"mi\">1</span><span class=\"w\"> </span><span class=\"n\">failure</span>\n</code></pre></div>\n<h3>Versions and Environment</h3>\n<p>Cranelift version or commit: main (e2dcb19099606f161c6d6145ba71130579b452e2)</p>\n<p>Operating system: Linux</p>\n<p>Architecture: RISCV64GC</p>\n<h3>Extra Info</h3>\n<p>CC: @yuyang-ok <br>\n</p>\n</blockquote>",
        "id": 340829446,
        "sender_full_name": "Wasmtime GitHub notifications bot",
        "timestamp": 1678446531
    }
]