[
    {
        "content": "<p>pchickey opened <a href=\"https://github.com/bytecodealliance/wasmtime/pull/2881\">PR #2881</a> from <code>pch/cargo_deny_ignore_RUSTSEC-2021-0064</code> to <code>main</code>:</p>\n<blockquote>\n<p>Transient dependencies depend on two different versions of <code>cpuid-bool</code>.</p>\n<p>This advisory does not appear to be urgent. We should review this ignore<br>\nafter a few weeks to see if our deps have switched over.</p>\n<p>text of the advisory:</p>\n<div class=\"codehilite\" data-code-language=\"Rust\"><pre><span></span><code><span class=\"n\">Issued</span><span class=\"w\"></span>\n<span class=\"n\">May</span><span class=\"w\"> </span><span class=\"mi\">6</span><span class=\"p\">,</span><span class=\"w\"> </span><span class=\"mi\">2021</span><span class=\"w\"></span>\n<span class=\"n\">Package</span><span class=\"w\"></span>\n<span class=\"n\">cpuid</span><span class=\"o\">-</span><span class=\"kt\">bool</span><span class=\"w\"> </span><span class=\"p\">(</span><span class=\"n\">crates</span><span class=\"p\">.</span><span class=\"n\">io</span><span class=\"p\">)</span><span class=\"w\"></span>\n<span class=\"n\">Type</span><span class=\"w\"></span>\n<span class=\"n\">Unmaintained</span><span class=\"w\"></span>\n<span class=\"n\">Details</span><span class=\"w\"></span>\n<span class=\"n\">https</span>:<span class=\"c1\">//github.com/RustCrypto/utils/pull/381</span>\n<span class=\"n\">Patched</span><span class=\"w\"></span>\n<span class=\"n\">no</span><span class=\"w\"> </span><span class=\"n\">patched</span><span class=\"w\"> </span><span class=\"n\">versions</span><span class=\"w\"></span>\n<span class=\"n\">Description</span><span class=\"w\"></span>\n<span class=\"n\">Please</span><span class=\"w\"> </span><span class=\"k\">use</span><span class=\"w\"> </span><span class=\"n\">the</span><span class=\"w\"> </span><span class=\"err\">`</span><span class=\"n\">cpufeatures</span><span class=\"err\">``</span><span class=\"w\"> </span><span class=\"k\">crate</span><span class=\"w\"> </span><span class=\"n\">going</span><span class=\"w\"> </span><span class=\"n\">forward</span>:\n\n<span class=\"nc\">https</span>:<span class=\"c1\">//github.com/RustCrypto/utils/tree/master/cpufeatures</span>\n\n<span class=\"n\">There</span><span class=\"w\"> </span><span class=\"n\">will</span><span class=\"w\"> </span><span class=\"n\">be</span><span class=\"w\"> </span><span class=\"n\">no</span><span class=\"w\"> </span><span class=\"n\">further</span><span class=\"w\"> </span><span class=\"n\">releases</span><span class=\"w\"> </span><span class=\"n\">of</span><span class=\"w\"> </span><span class=\"n\">cpuid</span><span class=\"o\">-</span><span class=\"kt\">bool</span><span class=\"p\">.</span><span class=\"w\"></span>\n</code></pre></div>\n<p>&lt;!--</p>\n<p>Please ensure that the following steps are all taken care of before submitting<br>\nthe PR.</p>\n<ul>\n<li>\n<p>[ ] This has been discussed in issue #..., or if not, please tell us why<br>\n  here.</p>\n</li>\n<li>\n<p>[ ] A short description of what this does, why it is needed; if the<br>\n  description becomes long, the matter should probably be discussed in an issue<br>\n  first.</p>\n</li>\n<li>\n<p>[ ] This PR contains test cases, if meaningful.</p>\n</li>\n<li>[ ] A reviewer from the core maintainer team has been assigned for this PR.<br>\n  If you don't know who could review this, please indicate so. The list of<br>\n  suggested reviewers on the right can help you.</li>\n</ul>\n<p>Please ensure all communication adheres to the <a href=\"https://github.com/bytecodealliance/wasmtime/blob/master/CODE_OF_CONDUCT.md\">code of\nconduct</a>.<br>\n--&gt;<br>\n</p>\n</blockquote>",
        "id": 237749318,
        "sender_full_name": "Wasmtime GitHub notifications bot",
        "timestamp": 1620346221
    },
    {
        "content": "<p>peterhuene submitted <a href=\"https://github.com/bytecodealliance/wasmtime/pull/2881#pullrequestreview-653986883\">PR Review</a>.</p>",
        "id": 237749391,
        "sender_full_name": "Wasmtime GitHub notifications bot",
        "timestamp": 1620346273
    },
    {
        "content": "<p>pchickey merged <a href=\"https://github.com/bytecodealliance/wasmtime/pull/2881\">PR #2881</a>.</p>",
        "id": 237751651,
        "sender_full_name": "Wasmtime GitHub notifications bot",
        "timestamp": 1620348191
    }
]