[
    {
        "content": "<p>olivierlemasle opened <a href=\"https://github.com/bytecodealliance/wasmtime/pull/3382\">PR #3382</a> from <code>types-license</code> to <code>main</code>:</p>\n<blockquote>\n<p>The LICENSE file is missing in wasmtime-types crate.</p>\n<p>As per the Apache 2.0 license, the license file itself should be redistributed with the source code.</p>\n</blockquote>",
        "id": 254431368,
        "sender_full_name": "Wasmtime GitHub notifications bot",
        "timestamp": 1632341522
    },
    {
        "content": "<p>cfallin submitted <a href=\"https://github.com/bytecodealliance/wasmtime/pull/3382#pullrequestreview-761364507\">PR review</a>.</p>",
        "id": 254432173,
        "sender_full_name": "Wasmtime GitHub notifications bot",
        "timestamp": 1632341854
    },
    {
        "content": "<p>cfallin merged <a href=\"https://github.com/bytecodealliance/wasmtime/pull/3382\">PR #3382</a>.</p>",
        "id": 254437110,
        "sender_full_name": "Wasmtime GitHub notifications bot",
        "timestamp": 1632343868
    }
]