[
    {
        "content": "<p>Kmeakin opened <a href=\"https://github.com/bytecodealliance/wasmtime/pull/6141\">PR #6141</a> from <code>Kmeakin:select-self</code> to <code>bytecodealliance:main</code>:</p>\n<blockquote>\n<p>Adds <code>select x x =&gt; x</code> and <code>bitselect x x =&gt; x</code> rewrites</p>\n</blockquote>",
        "id": 346929232,
        "sender_full_name": "Wasmtime GitHub notifications bot",
        "timestamp": 1680629946
    },
    {
        "content": "<p><strong>Kmeakin</strong> requested <a href=\"https://github.com/orgs/bytecodealliance/teams/wasmtime-compiler-reviewers\">wasmtime-compiler-reviewers</a> for a review on <a href=\"https://github.com/bytecodealliance/wasmtime/pull/6141\">PR #6141</a>.</p>",
        "id": 346929235,
        "sender_full_name": "Wasmtime GitHub notifications bot",
        "timestamp": 1680629947
    },
    {
        "content": "<p><strong>Kmeakin</strong> requested <a href=\"https://github.com/elliottt\">elliottt</a> for a review on <a href=\"https://github.com/bytecodealliance/wasmtime/pull/6141\">PR #6141</a>.</p>",
        "id": 346929236,
        "sender_full_name": "Wasmtime GitHub notifications bot",
        "timestamp": 1680629947
    }
]