[
    {
        "content": "<p>bnjbvr opened <a href=\"https://github.com/bytecodealliance/wasmtime/pull/1915\">PR #1915</a> from <code>x64-wip</code> to <code>master</code>:</p>\n<blockquote>\n<p>This makes it possible to run a simple recursive fibonacci function in<br>\nwasmtime, with the new x64 backend. Plenty of todos implemented as assertions that may and will trigger on larger programs, plenty of paths are still untested, still a lot of missing opcodes lowering and code gen, plenty of optimizations, etc etc.</p>\n</blockquote>",
        "id": 201872708,
        "sender_full_name": "Wasmtime GitHub notifications bot",
        "timestamp": 1593017138
    },
    {
        "content": "<p><strong>bnjbvr</strong> requested <a href=\"https://github.com/cfallin\">cfallin</a> and <a href=\"https://github.com/julian-seward1\">julian-seward1</a> for a review on <a href=\"https://github.com/bytecodealliance/wasmtime/pull/1915\">PR #1915</a>.</p>",
        "id": 201872709,
        "sender_full_name": "Wasmtime GitHub notifications bot",
        "timestamp": 1593017138
    },
    {
        "content": "<p><strong>bnjbvr</strong> requested <a href=\"https://github.com/cfallin\">cfallin</a> and <a href=\"https://github.com/julian-seward1\">julian-seward1</a> for a review on <a href=\"https://github.com/bytecodealliance/wasmtime/pull/1915\">PR #1915</a>.</p>",
        "id": 201872710,
        "sender_full_name": "Wasmtime GitHub notifications bot",
        "timestamp": 1593017138
    },
    {
        "content": "<p>cfallin submitted <a href=\"https://github.com/bytecodealliance/wasmtime/pull/1915#pullrequestreview-436835448\">PR Review</a>.</p>",
        "id": 201874194,
        "sender_full_name": "Wasmtime GitHub notifications bot",
        "timestamp": 1593017836
    },
    {
        "content": "<p>bjorn3 submitted <a href=\"https://github.com/bytecodealliance/wasmtime/pull/1915#pullrequestreview-436835647\">PR Review</a>.</p>",
        "id": 201874223,
        "sender_full_name": "Wasmtime GitHub notifications bot",
        "timestamp": 1593017852
    },
    {
        "content": "<p>bjorn3 created <a href=\"https://github.com/bytecodealliance/wasmtime/pull/1915#discussion_r445038279\">PR Review Comment</a>:</p>\n<blockquote>\n<p>Does space mean size or location?</p>\n</blockquote>",
        "id": 201874224,
        "sender_full_name": "Wasmtime GitHub notifications bot",
        "timestamp": 1593017852
    },
    {
        "content": "<p>cfallin created <a href=\"https://github.com/bytecodealliance/wasmtime/pull/1915#discussion_r445038768\">PR Review Comment</a>:</p>\n<blockquote>\n<p>Size, in this case (the <code>aarch64</code> impl is the same (and as an aside, we hope to factor out the commonalities here soon)).</p>\n</blockquote>",
        "id": 201874341,
        "sender_full_name": "Wasmtime GitHub notifications bot",
        "timestamp": 1593017897
    },
    {
        "content": "<p>cfallin submitted <a href=\"https://github.com/bytecodealliance/wasmtime/pull/1915#pullrequestreview-436836299\">PR Review</a>.</p>",
        "id": 201874342,
        "sender_full_name": "Wasmtime GitHub notifications bot",
        "timestamp": 1593017897
    },
    {
        "content": "<p>bjorn3 submitted <a href=\"https://github.com/bytecodealliance/wasmtime/pull/1915#pullrequestreview-436836843\">PR Review</a>.</p>",
        "id": 201874413,
        "sender_full_name": "Wasmtime GitHub notifications bot",
        "timestamp": 1593017942
    },
    {
        "content": "<p>bjorn3 created <a href=\"https://github.com/bytecodealliance/wasmtime/pull/1915#discussion_r445039156\">PR Review Comment</a>:</p>\n<blockquote>\n<div class=\"codehilite\"><pre><span></span><code>    ty.bits()\n</code></pre></div>\n\n\n</blockquote>",
        "id": 201874414,
        "sender_full_name": "Wasmtime GitHub notifications bot",
        "timestamp": 1593017942
    },
    {
        "content": "<p>bjorn3 submitted <a href=\"https://github.com/bytecodealliance/wasmtime/pull/1915#pullrequestreview-436868716\">PR Review</a>.</p>",
        "id": 201879871,
        "sender_full_name": "Wasmtime GitHub notifications bot",
        "timestamp": 1593020509
    },
    {
        "content": "<p>bjorn3 created <a href=\"https://github.com/bytecodealliance/wasmtime/pull/1915#discussion_r445063520\">PR Review Comment</a>:</p>\n<blockquote>\n<p>Why is it an <code>i64</code> then? A negative size doesn't make sense.</p>\n</blockquote>",
        "id": 201879872,
        "sender_full_name": "Wasmtime GitHub notifications bot",
        "timestamp": 1593020509
    },
    {
        "content": "<p>julian-seward1 submitted <a href=\"https://github.com/bytecodealliance/wasmtime/pull/1915#pullrequestreview-437208118\">PR Review</a>.</p>",
        "id": 201936934,
        "sender_full_name": "Wasmtime GitHub notifications bot",
        "timestamp": 1593067361
    },
    {
        "content": "<p>julian-seward1 created <a href=\"https://github.com/bytecodealliance/wasmtime/pull/1915#discussion_r445339252\">PR Review Comment</a>:</p>\n<blockquote>\n<p>pico-nit (smaller even than a nano-nit): These are now sign-extended loads <em>and</em> moves.</p>\n</blockquote>",
        "id": 201936935,
        "sender_full_name": "Wasmtime GitHub notifications bot",
        "timestamp": 1593067361
    },
    {
        "content": "<p>julian-seward1 submitted <a href=\"https://github.com/bytecodealliance/wasmtime/pull/1915#pullrequestreview-437208558\">PR Review</a>.</p>",
        "id": 201936959,
        "sender_full_name": "Wasmtime GitHub notifications bot",
        "timestamp": 1593067418
    },
    {
        "content": "<p>julian-seward1 created <a href=\"https://github.com/bytecodealliance/wasmtime/pull/1915#discussion_r445339599\">PR Review Comment</a>:</p>\n<blockquote>\n<p>atto-nit: (reg addr), but no imm</p>\n</blockquote>",
        "id": 201936960,
        "sender_full_name": "Wasmtime GitHub notifications bot",
        "timestamp": 1593067418
    },
    {
        "content": "<p>julian-seward1 submitted <a href=\"https://github.com/bytecodealliance/wasmtime/pull/1915#pullrequestreview-437210299\">PR Review</a>.</p>",
        "id": 201937103,
        "sender_full_name": "Wasmtime GitHub notifications bot",
        "timestamp": 1593067617
    },
    {
        "content": "<p>julian-seward1 created <a href=\"https://github.com/bytecodealliance/wasmtime/pull/1915#discussion_r445340969\">PR Review Comment</a>:</p>\n<blockquote>\n<p>Random comment: if at some point you add <code>tst</code> as an instruction, it has the same \"shape\" as <code>cmp</code> and so would fit naturally here.  (cmp = subtract operands, set flags, throw away result; tst = AND operands; set flags; throw away result).</p>\n</blockquote>",
        "id": 201937104,
        "sender_full_name": "Wasmtime GitHub notifications bot",
        "timestamp": 1593067617
    },
    {
        "content": "<p>bnjbvr updated <a href=\"https://github.com/bytecodealliance/wasmtime/pull/1915\">PR #1915</a> from <code>x64-wip</code> to <code>master</code>:</p>\n<blockquote>\n<p>This makes it possible to run a simple recursive fibonacci function in<br>\nwasmtime, with the new x64 backend. Plenty of todos implemented as assertions that may and will trigger on larger programs, plenty of paths are still untested, still a lot of missing opcodes lowering and code gen, plenty of optimizations, etc etc.</p>\n</blockquote>",
        "id": 201963857,
        "sender_full_name": "Wasmtime GitHub notifications bot",
        "timestamp": 1593089336
    },
    {
        "content": "<p>bnjbvr merged <a href=\"https://github.com/bytecodealliance/wasmtime/pull/1915\">PR #1915</a>.</p>",
        "id": 201975187,
        "sender_full_name": "Wasmtime GitHub notifications bot",
        "timestamp": 1593094835
    },
    {
        "content": "<p>bnjbvr submitted <a href=\"https://github.com/bytecodealliance/wasmtime/pull/1915#pullrequestreview-437543373\">PR Review</a>.</p>",
        "id": 201975233,
        "sender_full_name": "Wasmtime GitHub notifications bot",
        "timestamp": 1593094856
    },
    {
        "content": "<p>bnjbvr created <a href=\"https://github.com/bytecodealliance/wasmtime/pull/1915#discussion_r445595614\">PR Review Comment</a>:</p>\n<blockquote>\n<p>Thanks! Even updated the callers so they use ty.bits() instead.</p>\n</blockquote>",
        "id": 201975234,
        "sender_full_name": "Wasmtime GitHub notifications bot",
        "timestamp": 1593094856
    },
    {
        "content": "<p>bnjbvr submitted <a href=\"https://github.com/bytecodealliance/wasmtime/pull/1915#pullrequestreview-437543790\">PR Review</a>.</p>",
        "id": 201975302,
        "sender_full_name": "Wasmtime GitHub notifications bot",
        "timestamp": 1593094881
    },
    {
        "content": "<p>bnjbvr created <a href=\"https://github.com/bytecodealliance/wasmtime/pull/1915#discussion_r445595957\">PR Review Comment</a>:</p>\n<blockquote>\n<p>Good question; I'll take care of it during the Grand Refactoring.</p>\n</blockquote>",
        "id": 201975303,
        "sender_full_name": "Wasmtime GitHub notifications bot",
        "timestamp": 1593094881
    },
    {
        "content": "<p>bjorn3 created <a href=\"https://github.com/bytecodealliance/wasmtime/pull/1915#discussion_r447572895\">PR Review Comment</a>:</p>\n<blockquote>\n<p>*convention</p>\n</blockquote>",
        "id": 202416736,
        "sender_full_name": "Wasmtime GitHub notifications bot",
        "timestamp": 1593512103
    },
    {
        "content": "<p>bjorn3 submitted <a href=\"https://github.com/bytecodealliance/wasmtime/pull/1915#pullrequestreview-439873235\">PR Review</a>.</p>",
        "id": 202416737,
        "sender_full_name": "Wasmtime GitHub notifications bot",
        "timestamp": 1593512103
    },
    {
        "content": "<p>bjorn3 created <a href=\"https://github.com/bytecodealliance/wasmtime/pull/1915#discussion_r447576280\">PR Review Comment</a>:</p>\n<blockquote>\n<p>This should have used <code>next_vreg</code> instead of <code>next_gpr</code>.</p>\n</blockquote>",
        "id": 202417200,
        "sender_full_name": "Wasmtime GitHub notifications bot",
        "timestamp": 1593512471
    },
    {
        "content": "<p>bjorn3 submitted <a href=\"https://github.com/bytecodealliance/wasmtime/pull/1915#pullrequestreview-439877684\">PR Review</a>.</p>",
        "id": 202417201,
        "sender_full_name": "Wasmtime GitHub notifications bot",
        "timestamp": 1593512471
    }
]