[
    {
        "content": "<p>abrown opened <a href=\"https://github.com/bytecodealliance/wasmtime/pull/3764\">PR #3764</a> from <code>meeting-notes</code> to <code>main</code>:</p>\n<blockquote>\n<p>@cfallin, @alexcrichton, @fitzgen, @jlb6740: hopefully this captures what you meant; feel free to change if not.</p>\n</blockquote>",
        "id": 270587665,
        "sender_full_name": "Wasmtime GitHub notifications bot",
        "timestamp": 1643909696
    },
    {
        "content": "<p>cfallin submitted <a href=\"https://github.com/bytecodealliance/wasmtime/pull/3764#pullrequestreview-872197218\">PR review</a>.</p>",
        "id": 270588182,
        "sender_full_name": "Wasmtime GitHub notifications bot",
        "timestamp": 1643909901
    },
    {
        "content": "<p>abrown merged <a href=\"https://github.com/bytecodealliance/wasmtime/pull/3764\">PR #3764</a>.</p>",
        "id": 270589400,
        "sender_full_name": "Wasmtime GitHub notifications bot",
        "timestamp": 1643910378
    }
]