[
    {
        "content": "<p>alexcrichton opened <a href=\"https://github.com/bytecodealliance/wasmtime/pull/4695\">PR #4695</a> from <code>fix-ci</code> to <code>release-0.40.0</code>:</p>\n<blockquote>\n<p>This is a backport of <a href=\"https://github.com/bytecodealliance/wasmtime/commit/c1c48b4386edc17268c1acd66c3c22c67896ae4c\">https://github.com/bytecodealliance/wasmtime/commit/c1c48b4386edc17268c1acd66c3c22c67896ae4c</a> to ensure that the 0.40.0 release CI will be able to progress in a week or so.</p>\n</blockquote>",
        "id": 293012736,
        "sender_full_name": "Wasmtime GitHub notifications bot",
        "timestamp": 1660253647
    },
    {
        "content": "<p>abrown submitted <a href=\"https://github.com/bytecodealliance/wasmtime/pull/4695#pullrequestreview-1070407210\">PR review</a>.</p>",
        "id": 293015035,
        "sender_full_name": "Wasmtime GitHub notifications bot",
        "timestamp": 1660254754
    },
    {
        "content": "<p>alexcrichton merged <a href=\"https://github.com/bytecodealliance/wasmtime/pull/4695\">PR #4695</a>.</p>",
        "id": 293019606,
        "sender_full_name": "Wasmtime GitHub notifications bot",
        "timestamp": 1660257053
    }
]