[
    {
        "content": "<p>One question for the content API is how to sequence the publication of a package with the provisioning of storage, upload of content, and validation of content</p>",
        "id": 308470653,
        "sender_full_name": "Lann Martin",
        "timestamp": 1667854078
    },
    {
        "content": "<p>The \"current\" publish API has two phases, a \"draft\" publication created synchronously by the publisher and then a later asynchronous \"real\" publication after upload/validation</p>",
        "id": 308470736,
        "sender_full_name": "Lann Martin",
        "timestamp": 1667854111
    }
]