[
    {
        "content": "<p>well <span class=\"user-mention\" data-user-id=\"253990\">@Nick Fitzgerald</span> I had a nice review all lined up and ready to go, hit submit \"500 internal server error\"</p>",
        "id": 189034916,
        "sender_full_name": "Alex Crichton",
        "timestamp": 1582648100
    },
    {
        "content": "<p>oh man do I get an award for realizing github was down before their status page said so?</p>",
        "id": 189035515,
        "sender_full_name": "Alex Crichton",
        "timestamp": 1582648478
    },
    {
        "content": "<p>I suspect not</p>",
        "id": 189035521,
        "sender_full_name": "Alex Crichton",
        "timestamp": 1582648482
    },
    {
        "content": "<p>fwiw nobody can push either, so no new reviews will be coming</p>",
        "id": 189036273,
        "sender_full_name": "Yury Delendik",
        "timestamp": 1582648966
    },
    {
        "content": "<p><span class=\"user-mention\" data-user-id=\"253990\">@Nick Fitzgerald</span> yeah lemme take one more look and I'll merge</p>",
        "id": 189070010,
        "sender_full_name": "Alex Crichton",
        "timestamp": 1582671498
    }
]