[
    {
        "content": "<p>Currently it's extremely painful to find what I'm looking for in the sea of related crates (module, codegen, frontend, native, the 'prelude' crate, ...). Is there a rustdoc page that allows searching in all of these?</p>",
        "id": 197603376,
        "sender_full_name": "osa1",
        "timestamp": 1589483270
    },
    {
        "content": "<p><a href=\"https://docs.rs/wasmtime/0.16.0/wasmtime/\">https://docs.rs/wasmtime/0.16.0/wasmtime/</a> or just <code>cargo doc --open</code> locally</p>",
        "id": 197604971,
        "sender_full_name": "Pat Hickey",
        "timestamp": 1589483980
    },
    {
        "content": "<p>Sorry for dumb question, but how do I search for cranelift symbols in that page? For example if I search for <code>finalize_definitions</code> (a cranelift method) it doesn't find anything.</p>",
        "id": 197605283,
        "sender_full_name": "osa1",
        "timestamp": 1589484123
    },
    {
        "content": "<p>(I'm building the documentation locally atm)</p>",
        "id": 197605400,
        "sender_full_name": "osa1",
        "timestamp": 1589484191
    },
    {
        "content": "<p>OK, locally building docs inside cranelift dir works! Thanks!</p>",
        "id": 197606079,
        "sender_full_name": "osa1",
        "timestamp": 1589484562
    },
    {
        "content": "<p>ah, yeah, that search scope would be better locally than on <a href=\"http://docs.rs\">docs.rs</a>, since search will be for all workspace packages and deps, versus the entire <a href=\"http://crates.io\">crates.io</a> universe</p>",
        "id": 197607417,
        "sender_full_name": "Pat Hickey",
        "timestamp": 1589485261
    }
]