[
    {
        "content": "<p>COFF isn't supported properly yet?</p>",
        "id": 195687215,
        "sender_full_name": "Carlo Kok",
        "timestamp": 1588155221
    },
    {
        "content": "<p><code>cranelift-object</code> should support COFF/PE</p>",
        "id": 195690397,
        "sender_full_name": "bjorn3",
        "timestamp": 1588157286
    },
    {
        "content": "<p>I got an error when using module::finish.</p>",
        "id": 195701321,
        "sender_full_name": "Carlo Kok",
        "timestamp": 1588163866
    },
    {
        "content": "<p>\"Coff not supported\" or something along those lines.</p>",
        "id": 195701337,
        "sender_full_name": "Carlo Kok",
        "timestamp": 1588163873
    },
    {
        "content": "<p>Is there a backtrace? Or is it just a plain error and not a panic?</p>",
        "id": 195721756,
        "sender_full_name": "bjorn3",
        "timestamp": 1588172094
    },
    {
        "content": "<p>Sounds like you are using <code>cranelift-faerie</code>, which doesn't support COFF. Use <code>cranelift-object</code> instead, its COFF support hasn't been used much yet so it may have bugs (please report if you find any), but it should at least succeed at module::finish.</p>",
        "id": 195788655,
        "sender_full_name": "Philip Craig",
        "timestamp": 1588208212
    },
    {
        "content": "<p>thanks! yes I was. Whats the difference between the two?</p>",
        "id": 195798920,
        "sender_full_name": "Carlo Kok",
        "timestamp": 1588223139
    },
    {
        "content": "<p>(Object works fine, at least it emits coff just fine)</p>",
        "id": 195799542,
        "sender_full_name": "Carlo Kok",
        "timestamp": 1588224066
    },
    {
        "content": "<p>For cranelift users, the main difference is the COFF support. If you want to interact directly with the faerie or object APIs then the difference is that they operate at different abstraction levels (object tends to be lower level).</p>",
        "id": 195801824,
        "sender_full_name": "Philip Craig",
        "timestamp": 1588227561
    }
]