[
    {
        "content": "<p>Can the Wasi-sdk handle the c++ <code>new (nothrow)</code> ?</p>",
        "id": 355623988,
        "sender_full_name": "Scott Waye",
        "timestamp": 1683156154
    },
    {
        "content": "<p>Yes</p>",
        "id": 355625077,
        "sender_full_name": "Dan Gohman",
        "timestamp": 1683156887
    },
    {
        "content": "<p>I need to investigate more as I'm getting an <code>undefined_stub</code> I think.  But let me spend more time on it.  Thanks</p>",
        "id": 355626989,
        "sender_full_name": "Scott Waye",
        "timestamp": 1683158189
    },
    {
        "content": "<p><span class=\"user-mention silent\" data-user-id=\"395878\">Scott Waye</span> has marked this topic as resolved.</p>",
        "id": 355630504,
        "sender_full_name": "Notification Bot",
        "timestamp": 1683160375
    }
]